macros/__init__.py
theme/__init__.py
theme/base.html
theme/highlight.min.js
theme/logo.svg
theme/main.html
theme/mkdocs_theme.yml
theme/nav.html
theme/search.html
theme/styles.css
theme/fonts/pt-serif-v17-latin-regular.woff
theme/fonts/pt-serif-v17-latin-regular.woff2
mkdocs_conia-0.1.12.dist-info/LICENSE.md
mkdocs_conia-0.1.12.dist-info/METADATA
mkdocs_conia-0.1.12.dist-info/WHEEL
mkdocs_conia-0.1.12.dist-info/entry_points.txt
mkdocs_conia-0.1.12.dist-info/top_level.txt
mkdocs_conia-0.1.12.dist-info/RECORD
