Metadata-Version: 2.1
Name: mkdocs-conia
Version: 0.1.12
Summary: Default mkdocs theme for Conia projects
Home-page: https://github.com/coniadev/mkdocs-conia
Author: ebene fünf GmbH
Author-email: conia@ebenefuenf.de
License: MIT
License-File: LICENSE.md
Requires-Dist: mkdocs >=1.3
Requires-Dist: mkdocs-macros-plugin >=0.7
Requires-Dist: pymdown-extensions >=10.3
